water_futures_battle/VERSION
water_futures_battle/__init__.py
water_futures_battle/base_model/__init__.py
water_futures_battle/base_model/entities.py
water_futures_battle/base_model/properties.py
water_futures_battle/climate/__init__.py
water_futures_battle/climate/dynamic_properties.py
water_futures_battle/climate/services.py
water_futures_battle/connections/__init__.py
water_futures_battle/connections/entities.py
water_futures_battle/connections/services.py
water_futures_battle/economy/__init__.py
water_futures_battle/economy/dynamic_properties.py
water_futures_battle/economy/entities.py
water_futures_battle/economy/services.py
water_futures_battle/energy/__init__.py
water_futures_battle/energy/dynamic_properties.py
water_futures_battle/energy/entities.py
water_futures_battle/energy/services.py
water_futures_battle/jurisdictions/__init__.py
water_futures_battle/jurisdictions/dynamic_properties.py
water_futures_battle/jurisdictions/entities.py
water_futures_battle/jurisdictions/enums.py
water_futures_battle/jurisdictions/services.py
water_futures_battle/national_context/__init__.py
water_futures_battle/national_context/entities.py
water_futures_battle/nrw_model/__init__.py
water_futures_battle/nrw_model/dynamic_properties.py
water_futures_battle/nrw_model/entities.py
water_futures_battle/nrw_model/enums.py
water_futures_battle/nrw_model/services.py
water_futures_battle/pipes/__init__.py
water_futures_battle/pipes/dynamic_properties.py
water_futures_battle/pipes/entities.py
water_futures_battle/pumping_stations/__init__.py
water_futures_battle/pumping_stations/dynamic_properties.py
water_futures_battle/pumping_stations/entities.py
water_futures_battle/pumping_stations/services.py
water_futures_battle/pumps/__init__.py
water_futures_battle/pumps/dynamic_properties.py
water_futures_battle/pumps/entities.py
water_futures_battle/py.typed
water_futures_battle/services.py
water_futures_battle/sources/__init__.py
water_futures_battle/sources/entities.py
water_futures_battle-0.4.0.dist-info/licenses/LICENSE
water_futures_battle-0.4.0.dist-info/WHEEL
water_futures_battle-0.4.0.dist-info/METADATA
water_futures_battle-0.4.0.dist-info/RECORD
