Metadata-Version: 2.4
Name: water-futures-battle
Version: 0.4.0
Summary: Python project for the Battle of the Water Futures, originally developed to be hosted at WDSA/CCWI 2026 conference, May 18-21, Paphos, Cyprus.
Keywords: water,urban water systems,smart cities,battle,competition,battle water networks,planning,deep uncertainties,decision-making
Author: Dennis Zanutto, Christos Michalopoulos, Lydia Tsiami, André Artelt, Jasmin Brandt, Stelios Vrachimis, Stefano Alvisi, Valentina Marsili, Filippo Mazzoni, Panagiotis Samartzis, Demetrios Eliades
Author-email: Dennis Zanutto <dennis.zanutto@polimi.it>
License-Expression: MIT
License-File: LICENSE
Classifier: Development Status :: 3 - Alpha
Classifier: License :: OSI Approved :: MIT License
Classifier: Natural Language :: English
Classifier: Operating System :: Microsoft :: Windows
Classifier: Operating System :: MacOS
Classifier: Operating System :: POSIX :: Linux
Classifier: Programming Language :: Python
Classifier: Programming Language :: Python :: 3
Classifier: Programming Language :: Python :: 3.11
Classifier: Programming Language :: Python :: 3.12
Classifier: Programming Language :: Python :: 3.13
Classifier: Programming Language :: Python :: 3.14
Requires-Dist: openpyxl>=3.1.5
Requires-Dist: pandas>=2.3.3
Requires-Dist: pyyaml>=6.0.3
Requires-Dist: typer
Requires-Dist: epanet-plus>=0.1.3
Requires-Dist: rich>=14.2.0
Requires-Dist: requests>=2.32.5
Maintainer: Dennis Zanutto, André Artelt, Christos Michalopoulos
Maintainer-email: Dennis Zanutto <dennis.zanutto@polimi.it>
Requires-Python: >=3.11
Project-URL: Documentation, https://waterfutures.github.io/water-futures-battle/
Project-URL: Paper, https://arxiv.org/abs/2511.22986
Project-URL: Repository, https://github.com/WaterFutures/water-futures-battle
Project-URL: Zenodo, https://doi.org/10.5281/zenodo.17698299
